hmm/__init__.py
hmm/base.py
hmm/observe_float.py
hmm/simple.py
tests/__init__.py
tests/test_base.py
tests/test_observe_float.py
tests/test_simple.py
hmm4ds-0.0.6.dist-info/METADATA
hmm4ds-0.0.6.dist-info/WHEEL
hmm4ds-0.0.6.dist-info/top_level.txt
hmm4ds-0.0.6.dist-info/RECORD
