Metadata-Version: 2.1
Name: hmm4ds
Version: 0.0.6
Summary: Python code for hidden markov models
Home-page: https://github.com/fraserphysics/hmm
Author: Andrew Fraser
Author-email: andy@fraserphysics.com
License: UNKNOWN
Project-URL: Bug Tracker, https://github.com/fraserphysics/hmm/issues
Platform: UNKNOWN
Classifier: Programming Language :: Python :: 3
Classifier: License :: OSI Approved :: GNU General Public License v3 or later (GPLv3+)
Classifier: Operating System :: OS Independent
Requires-Python: >=3.7
Requires-Dist: numpy (>=1.17.0)
